cropclassification/__init__.py
cropclassification/calc_marker.py
cropclassification/calc_periodic_mosaic.py
cropclassification/cropclassification.py
cropclassification/general.ini
cropclassification/version.txt
cropclassification/helpers/__init__.py
cropclassification/helpers/config_helper.py
cropclassification/helpers/dir_helper.py
cropclassification/helpers/log_helper.py
cropclassification/helpers/model_helper.py
cropclassification/helpers/pandas_helper.py
cropclassification/postprocess/__init__.py
cropclassification/postprocess/classification_postprocess.py
cropclassification/postprocess/classification_reporting.py
cropclassification/postprocess/html_rapport_script.js
cropclassification/postprocess/html_rapport_template.html
cropclassification/postprocess/html_rapport_test.py
cropclassification/predict/__init__.py
cropclassification/predict/classification.py
cropclassification/predict/classification_keras.py
cropclassification/predict/classification_sklearn.py
cropclassification/predict/multicrop.py
cropclassification/preprocess/__init__.py
cropclassification/preprocess/_classification_preprocess_BEFL.py
cropclassification/preprocess/_timeseries_calc_openeo.py
cropclassification/preprocess/_timeseries_helper.py
cropclassification/preprocess/classification_preprocess.py
cropclassification/preprocess/timeseries.py
cropclassification/util/__init__.py
cropclassification/util/date_util.py
cropclassification/util/geoops_util.py
cropclassification/util/io_util.py
cropclassification/util/mosaic_util.py
cropclassification/util/openeo_util.py
cropclassification/util/raster_index_util.py
cropclassification/util/raster_util.py
cropclassification/util/zonal_stats_bulk/__init__.py
cropclassification/util/zonal_stats_bulk/_general_helper.py
cropclassification/util/zonal_stats_bulk/_processing_util.py
cropclassification/util/zonal_stats_bulk/_raster_helper.py
cropclassification/util/zonal_stats_bulk/_vector_helper.py
cropclassification-0.2.dist-info/METADATA
cropclassification-0.2.dist-info/WHEEL
cropclassification-0.2.dist-info/entry_points.txt
cropclassification-0.2.dist-info/top_level.txt
cropclassification-0.2.dist-info/RECORD
