Metadata-Version: 2.1
Name: cropclassification
Version: 0.2
Summary: Package to classify crops based on sentinel images.
Home-page: https://github.com/theroggy/cropclassification
Author: Pieter Roggemans
Author-email: pieter.roggemans@gmail.com
Classifier: Programming Language :: Python :: 3
Classifier: Operating System :: OS Independent
Requires-Python: >=3.9
Requires-Dist: geofileops
Requires-Dist: geopandas
Requires-Dist: openeo
Requires-Dist: psutil
Requires-Dist: rasterio
Requires-Dist: rasterstats
Requires-Dist: rioxarray
Requires-Dist: scikit-learn
Requires-Dist: tensorflow
